bsread/__init__.py
bsread/consts.py
bsread/dispatcher.py
bsread/sender.py
bsread/source.py
bsread/utils.py
bsread/cli/__init__.py
bsread/cli/avail.py
bsread/cli/bs.py
bsread/cli/config.py
bsread/cli/create.py
bsread/cli/h5.py
bsread/cli/receive.py
bsread/cli/simulate.py
bsread/cli/stats.py
bsread/cli/utils/__init__.py
bsread/cli/utils/create_test_db.py
bsread/cli/utils/utils.py
bsread/cli/utils/writer.py
bsread/cli/utils/tables/__init__.py
bsread/cli/utils/tables/bases.py
bsread/cli/utils/tables/classic.py
bsread/cli/utils/tables/data.py
bsread/cli/utils/tables/plain.py
bsread/cli/utils/tables/rich.py
bsread/cli/utils/tables/textual.py
bsread/data/__init__.py
bsread/data/compression.py
bsread/data/helpers.py
bsread/data/serialization.py
bsread/handlers/__init__.py
bsread/handlers/compact.py
bsread/handlers/extended.py
psi_bsread-2.0.1.dist-info/LICENSE
psi_bsread-2.0.1.dist-info/METADATA
psi_bsread-2.0.1.dist-info/WHEEL
psi_bsread-2.0.1.dist-info/top_level.txt
psi_bsread-2.0.1.dist-info/RECORD
