Metadata-Version: 2.1
Name: psi-bsread
Version: 2.0.1
Summary: bsread for Python
Home-page: https://github.com/paulscherrerinstitute/bsread_python
Author: Paul Scherrer Institute
License: GNU GPLv3
License-File: LICENSE
Requires-Dist: psi-mflow
Requires-Dist: click
Requires-Dist: numpy
Requires-Dist: pyzmq
Requires-Dist: requests
Requires-Dist: lz4
Requires-Dist: bitshuffle
